keyword_detection/__init__.py
keyword_detection/keyword_detection.py
keyword_detection/license_manager.py
keyword_detection/encrypted/detection.wasm
keyword_detection/pyarmor_runtime_000000/__init__.py
keyword_detection/pyarmor_runtime_000000/pyarmor_runtime.so
keyword_detection_lib-1.0.15.dist-info/METADATA
keyword_detection_lib-1.0.15.dist-info/WHEEL
keyword_detection_lib-1.0.15.dist-info/top_level.txt
keyword_detection_lib-1.0.15.dist-info/RECORD
